setup.py
graphmanagerlib/Complex_Data_For_Gcn.py
graphmanagerlib/Complex_Graph.py
graphmanagerlib/Document.py
graphmanagerlib/GCN.py
graphmanagerlib/GraphManager.py
graphmanagerlib/Inference.py
graphmanagerlib/JsonManager.py
graphmanagerlib/Model_formation.py
graphmanagerlib/Node.py
graphmanagerlib/__init__.py
graphmanagerlib.egg-info/PKG-INFO
graphmanagerlib.egg-info/SOURCES.txt
graphmanagerlib.egg-info/dependency_links.txt
graphmanagerlib.egg-info/requires.txt
graphmanagerlib.egg-info/top_level.txt