Metadata-Version: 1.0
Name: graphmanagerlib
Version: 4.1.6
Summary: My first Python library
Home-page: UNKNOWN
Author: Cambier Damien
Author-email: UNKNOWN
License: MIT
Platform: UNKNOWN
